rabbitmq_testclient/RabbitMQClient.py
rabbitmq_testclient/__init__.py
rabbitmq_testclient/exceptions.py
rabbitmq_testclient/settings.py
rabbitmq_testclient-0.1.0.dist-info/METADATA
rabbitmq_testclient-0.1.0.dist-info/WHEEL
rabbitmq_testclient-0.1.0.dist-info/RECORD
